CHANGELOG.rst
LICENSE.rst
MANIFEST.in
README.rst
setup.py
magni/__init__.py
magni.egg-info/PKG-INFO
magni.egg-info/SOURCES.txt
magni.egg-info/dependency_links.txt
magni.egg-info/requires.txt
magni.egg-info/top_level.txt
magni/afm/__init__.py
magni/afm/_config.py
magni/afm/reconstruction.py
magni/afm/io/__init__.py
magni/afm/io/_data_attachment.py
magni/afm/io/_object_building.py
magni/afm/io/_stream_conversion.py
magni/afm/io/_util.py
magni/afm/types/__init__.py
magni/afm/types/_util.py
magni/afm/types/image.py
magni/afm/types/spectroscopy.py
magni/cs/__init__.py
magni/cs/indicators.py
magni/cs/phase_transition/__init__.py
magni/cs/phase_transition/_analysis.py
magni/cs/phase_transition/_backup.py
magni/cs/phase_transition/_config.py
magni/cs/phase_transition/_data.py
magni/cs/phase_transition/_simulation.py
magni/cs/phase_transition/_util.py
magni/cs/phase_transition/io.py
magni/cs/phase_transition/plotting.py
magni/cs/reconstruction/__init__.py
magni/cs/reconstruction/_config.py
magni/cs/reconstruction/amp/__init__.py
magni/cs/reconstruction/amp/_algorithm.py
magni/cs/reconstruction/amp/_config.py
magni/cs/reconstruction/amp/stop_criterion.py
magni/cs/reconstruction/amp/threshold_operator.py
magni/cs/reconstruction/amp/util.py
magni/cs/reconstruction/gamp/__init__.py
magni/cs/reconstruction/gamp/_algorithm.py
magni/cs/reconstruction/gamp/_config.py
magni/cs/reconstruction/gamp/channel_initialisation.py
magni/cs/reconstruction/gamp/input_channel.py
magni/cs/reconstruction/gamp/output_channel.py
magni/cs/reconstruction/gamp/stop_criterion.py
magni/cs/reconstruction/iht/__init__.py
magni/cs/reconstruction/iht/_config.py
magni/cs/reconstruction/it/__init__.py
magni/cs/reconstruction/it/_algorithm.py
magni/cs/reconstruction/it/_config.py
magni/cs/reconstruction/it/_step_size.py
magni/cs/reconstruction/it/_stop_criterion.py
magni/cs/reconstruction/it/_threshold.py
magni/cs/reconstruction/it/_threshold_operators.py
magni/cs/reconstruction/it/_util.py
magni/cs/reconstruction/sl0/_L_start.py
magni/cs/reconstruction/sl0/_L_update.py
magni/cs/reconstruction/sl0/__init__.py
magni/cs/reconstruction/sl0/_algorithm.py
