Metadata-Version: 1.1
Name: magni
Version: 1.6.0
Summary: A Python Package for Compressive Sampling and Reconstruction of Atomic Force Microscopy Images
Home-page: https://github.com/SIP-AAU/Magni
Author: Magni Developers
Author-email: magni@es.aau.dk
License: BSD 2-Clause
Download-URL: https://pypi.python.org/pypi/magni
Keywords: Atomic Force Microscopy; Compressive Sensing; Python; Image Reconstruction; Reproducible Research
Platform: UNKNOWN
Classifier: Development Status :: 5 - Production/Stable
Classifier: Environment :: Console
Classifier: Intended Audience :: Science/Research
Classifier: License :: OSI Approved :: BSD License
Classifier: Natural Language :: English
Classifier: Operating System :: OS Independent
Classifier: Programming Language :: Python
Classifier: Programming Language :: Python :: 2
Classifier: Programming Language :: Python :: 2.7
Classifier: Programming Language :: Python :: 3
Classifier: Programming Language :: Python :: 3.3
Classifier: Programming Language :: Python :: 3.4
Classifier: Programming Language :: Python :: 3.5
Classifier: Topic :: Scientific/Engineering :: Image Recognition
Classifier: Topic :: Scientific/Engineering :: Information Analysis
Classifier: Topic :: Scientific/Engineering :: Mathematics
Classifier: Topic :: Scientific/Engineering :: Physics
Classifier: Topic :: Scientific/Engineering :: Visualization
